__init__.py
tasks.py
platinfra/__init__.py
platinfra/cli/__init__.py
platinfra/cli/cli.py
platinfra/enums/__init__.py
platinfra/enums/cloud_provider.py
platinfra/enums/deployment_type.py
platinfra/modules/applications/cloud_infra/data_versioning/lakefs/lakefs_cloud_infra.yaml
platinfra/modules/applications/cloud_infra/data_versioning/lakefs/tf_module/lakefs-dynamodb-config.tpl
platinfra/modules/applications/cloud_infra/data_versioning/lakefs/tf_module/lakefs-postgres-config.tpl
platinfra/modules/applications/cloud_infra/data_versioning/lakefs/tf_module/main.tf
platinfra/modules/applications/cloud_infra/data_versioning/lakefs/tf_module/outputs.tf
platinfra/modules/applications/cloud_infra/data_versioning/lakefs/tf_module/remote-cloud-init.tpl
platinfra/modules/applications/cloud_infra/data_versioning/lakefs/tf_module/simple-cloud-init.tpl
platinfra/modules/applications/cloud_infra/data_versioning/lakefs/tf_module/variables.tf
platinfra/modules/applications/cloud_infra/experiment_tracking/mlflow/mlflow_cloud_infra.yaml
platinfra/modules/applications/cloud_infra/experiment_tracking/mlflow/mlflow_kubernetes.yaml
platinfra/modules/applications/cloud_infra/experiment_tracking/mlflow/tf_module/main.tf
platinfra/modules/applications/cloud_infra/experiment_tracking/mlflow/tf_module/outputs.tf
platinfra/modules/applications/cloud_infra/experiment_tracking/mlflow/tf_module/remote-cloud-init.tpl
platinfra/modules/applications/cloud_infra/experiment_tracking/mlflow/tf_module/simple-cloud-init.tpl
platinfra/modules/applications/cloud_infra/experiment_tracking/mlflow/tf_module/variables.tf
platinfra/modules/applications/cloud_infra/experiment_tracking/wandb/wandb_cloud_infra.yaml
platinfra/modules/applications/cloud_infra/experiment_tracking/wandb/wandb_kubernetes.yaml
platinfra/modules/applications/cloud_infra/experiment_tracking/wandb/tf_module/main.tf
platinfra/modules/applications/cloud_infra/experiment_tracking/wandb/tf_module/outputs.tf
platinfra-0.0.1.dist-info/LICENSE
platinfra-0.0.1.dist-info/LICENSE_HEADER.txt
platinfra-0.0.1.dist-info/METADATA
platinfra-0.0.1.dist-info/WHEEL
platinfra-0.0.1.dist-info/entry_points.txt
platinfra-0.0.1.dist-info/top_level.txt
platinfra-0.0.1.dist-info/RECORD
