Metadata-Version: 2.1
Name: platinfra
Version: 0.0.1
Summary: A tool to help anyone deploy mlops tooling at the click of a button.
Author-email: Ali Abbas Jaffri <ali.abbasjaffri@live.com>
Maintainer-email: Ali Abbas Jaffri <ali.abbasjaffri@live.com>
License: Apache License
Project-URL: Homepage, https://github.com/platinfra/platinfra
Project-URL: Repository, https://github.com/platinfra/platinfra.git
Project-URL: Documentation, https://platinfra.github.io/
Keywords: platinfra
Classifier: Development Status :: 3 - Alpha
Classifier: Intended Audience :: Developers
Classifier: Intended Audience :: Science/Research
Classifier: License :: OSI Approved :: Apache Software License
Classifier: Operating System :: OS Independent
Classifier: Programming Language :: Python :: 3
Classifier: Topic :: Scientific/Engineering
Classifier: Topic :: Scientific/Engineering :: Artificial Intelligence
Classifier: Topic :: Software Development
Classifier: Topic :: Software Development :: Libraries :: Python Modules
Classifier: Topic :: Utilities
Classifier: Topic :: System :: Distributed Computing
Requires-Python: >3.10
License-File: LICENSE
License-File: LICENSE_HEADER.txt
Requires-Dist: invoke
Requires-Dist: boto3
Requires-Dist: pyyaml
Requires-Dist: black
Requires-Dist: pytest
Requires-Dist: mypy
Provides-Extra: docs
Requires-Dist: mkdocs-material ; extra == 'docs'
Requires-Dist: mkdocs-git-revision-date-localized-plugin ; extra == 'docs'
